{
    "habitat_map": {
        "legends": [
            {
                "legend_id": "habitats",
                "legend_title": {
                    "en": "Habitats",
                    "es": "Spanish legend title"
                },
                "entries": [
                    {
                        "entry_id": "agriculture",
                        "fill": "#73e2ec",
                        "type": "value",
                        "label": {
                            "en": "Agriculture",
                            "es": "Spanish agriculture"
                        }
                    },
                    {
                        "entry_id": "banana",
                        "fill": "#c1bc15",
                        "type": "value",
                        "label": {
                            "en": "Banana",
                            "es": "Spanish banana"
                        }
                    },
                    {
                        "entry_id": "bare_ground",
                        "fill": "#e9d4e6",
                        "type": "value",
                        "label": {
                            "en": "Bare ground",
                            "es": "Spanish bare ground"
                        }
                    },
                    {
                        "entry_id": "forest",
                        "fill": "#266b3a",
                        "type": "value",
                        "label": {
                            "en": "Forest",
                            "es": "Spanish forest"
                        }
                    },
                    {
                        "entry_id": "forest_agriculture_mix",
                        "fill": "#1ede45",
                        "type": "value",
                        "label": {
                            "en": "Forest/agriculture mix",
                            "es": "Spanish forest/agriculture mix"
                        }
                    },
                    {
                        "entry_id": "forest_agriculture_grassland_mix",
                        "fill": "#e26e7b",
                        "type": "value",
                        "label": {
                            "en": "Forest/agriculture/grassland mix",
                            "es": "Spanish Forests/agriculture/grassland mix"
                        }
                    },
                    {
                        "entry_id": "grassland",
                        "fill": "#e77919",
                        "type": "value",
                        "label": {
                            "en": "Grassland",
                            "es": "Spanish grassland"
                        }
                    },
                    {
                        "entry_id": "mangrove",
                        "fill": "#9f148f",
                        "type": "value",
                        "label": {
                            "en": "Mangrove",
                            "es": "Spanish mangrove"
                        }
                    },
                    {
                        "entry_id": "palm",
                        "fill": "#0ddd9f",
                        "type": "value",
                        "label": {
                            "en": "Palm",
                            "es": "Spanish palm"
                        }
                    },
                    {
                        "entry_id": "rivers",
                        "fill": "#480df8",
                        "type": "value",
                        "label": {
                            "en": "Rivers",
                            "es": "Spanish rivers"
                        }
                    },
                    {
                        "entry_id": "scrub",
                        "fill": "#643913",
                        "type": "value",
                        "label": {
                            "en": "Scrub",
                            "es": "Spanish scrub"
                        }
                    },
                    {
                        "entry_id": "snow",
                        "fill": "#fafff7",
                        "type": "value",
                        "label": {
                            "en": "Snow",
                            "es": "Spanish snow"
                        }
                    },
                    {
                        "entry_id": "urban",
                        "fill": "#232323",
                        "type": "value",
                        "label": {
                            "en": "Urban",
                            "es": "Spanish urban"
                        }
                    },
                    {
                        "entry_id": "waterbodies",
                        "fill": "#480df8",
                        "type": "value",
                        "label": {
                            "en": "Waterbodies",
                            "es": "Spanish waterbodies"
                        }
                    },
                    {
                        "entry_id": "wetland",
                        "fill": "#7f2edb",
                        "type": "value",
                        "label": {
                            "en": "Wetland",
                            "es": "Spanish wetland"
                        }
                    },
                    {
                        "entry_id": "wetland_open_water",
                        "fill": "#4868d2",
                        "type": "value",
                        "label": {
                            "en": "Wetland (open water)",
                            "es": "Spanish wetland (open water)"
                        }
                    }
                ]
            }    
        ]
    },
    "water_regulation_opportunities": {
        "legends": [
            {
                "legend_id": "opportunities",
                "legend_title": {
                    "en": "Opportunities",
                    "es": "Spanish legend title"
                },
                "entries": [
                    {
                        "entry_id": "lower",
                        "fill": "#306b10",
                        "type": "value",
                        "label": {
                            "en": "Opportunities in the lower catchment",
                            "es": "Spanish lower catchment opportunities"
                        }
                    },
                    {
                        "entry_id": "mid",
                        "fill": "#38b6f4",
                        "type": "value",
                        "label": {
                            "en": "Opportunities in the mid catchment",
                            "es": "Spanish mid catchment opportunities"
                        }
                    },
                    {
                        "entry_id": "upper",
                        "fill": "#4623e4",
                        "type": "value",
                        "label": {
                            "en": "Opportunities in the upper catchment",
                            "es": "Spanish upper catchment opportunities"
                        }
                    }
                ]
            }
        ]
    },
    "key_ecosystem_service_areas": {
        "legends": [
            {
                "legend_id": "important_areas",
                "legend_title": {
                    "en": "Areas important for both biodiversity and surface water regulation",
                    "es": "Spanish legend title"
                },
                "entries": [
                    {
                        "entry_id": "important_areas",
                        "fill": "#4aa933",
                        "stroke": "black",
                        "type": "line",
                        "label": {
                            "en": "Areas important for both biodiversity and surface water regulation",
                            "es": "Spanish areas important for both biodiversity and surface water regulation"
                        }
                    }
                ]
            },
            {
                "legend_id": "urban_and_roads",
                "legend_title": {
                    "en": "Urban and roads",
                    "es": "Spanish legend title"
                },
                "entries": [
                    {
                        "entry_id": "urban_and_roads",
                        "fill": "#bbbbbb",
                        "type": "value",
                        "label": {
                            "en": "Urban and roads",
                            "es": "Spanish urban and roads"
                        }
                    }
                ]
            }
        ]
    }
}
